downloadMusicVK
