Metadata-Version: 1.0
Name: dwnlMusicVK
Version: 0.1.2a3
Summary: Download all your music VK.
Home-page: https://github.com/akanoi/DownloadMusicVK
Author: Akanoi
Author-email: UNKNOWN
License: GNU
Platform: UNKNOWN
